<?xml version="1.0" encoding="utf-8"?>
<GenericMsg xmlns:xsd="http://www.w3.org/2001/XMLSchema" xmlns:xsi="http://www.w3.org/2001/XMLSchema-instance">
  <Header>
    <StartOfMessage>3405691582</StartOfMessage>
    <MessageType>VIP_DOWNLOAD_BIOMETRIC_SIGNATURES</MessageType>
    <SequenceNumber>5</SequenceNumber>
    <Status>SENDER</Status>
    <BodyLength>0</BodyLength>
    <TimeStamp>0</TimeStamp>
    <BodyCRC>0</BodyCRC>
    <HeaderCRC>0</HeaderCRC>
  </Header>
  <Body>
    <Item Type="Integer" Size="4" Name="DeviceID">1</Item>
    <Item Type="Integer" Size="4" Name="NumberOfSignatures">2</Item>
    <Item Type="ASCII_Var" Size="10" Name="Badge1">BADGE3001</Item>
    <Item Type="ASCII_Var" Size="5" Name="Pin1">1234</Item>
	<Item Type="ASCII_Var" Size="10" Name="Badge2">BADGE3002</Item>
    <Item Type="ASCII_Var" Size="5" Name="Pin2">1234</Item>
  </Body>
</GenericMsg>